{"name":"Create a new user account","id":"add-to-cart-functionality;create-a-new-user-account","testSteps":[{"number":1,"description":"Given enter the page","duration":6486,"startTime":"2024-07-20T16:29:42.509852400-05:00[America/Bogota]","screenshots":[{"screenshot":"a3b115e67132daac7f387f053ca240c1a27d60782eb9889c90c9eed01b2c8283.png","timeStamp":1721510988996}],"result":"SUCCESS","precondition":false,"level":0,"lineNumber":0,"children":[{"number":2,"description":"Juan open up","duration":6465,"startTime":"2024-07-20T16:29:42.517854200-05:00[America/Bogota]","screenshots":[{"screenshot":"a3b115e67132daac7f387f053ca240c1a27d60782eb9889c90c9eed01b2c8283.png","timeStamp":1721510988983}],"result":"SUCCESS","precondition":false,"level":1,"lineNumber":0,"children":[{"number":3,"description":"Juan opens the Utest page","duration":3272,"startTime":"2024-07-20T16:29:42.522856200-05:00[America/Bogota]","screenshots":[{"screenshot":"026f173daae99e80d9b75ffe4b6a0df59d738e7fc239c068033782054bb3ed5b.png","timeStamp":1721510985795}],"result":"SUCCESS","precondition":false,"level":2,"lineNumber":0}]}]},{"number":4,"description":"When enter the username \"Juan9090\"","duration":699,"startTime":"2024-07-20T16:29:48.997017200-05:00[America/Bogota]","screenshots":[{"screenshot":"dd0ed5af1eb946c34008ec07e9176bd7e33a1778797b99dec63e2bbe778f90cd.png","timeStamp":1721510989696}],"result":"SUCCESS","precondition":false,"level":0,"lineNumber":0,"children":[{"number":5,"description":"Juan fill username","duration":685,"startTime":"2024-07-20T16:29:49.004018900-05:00[America/Bogota]","screenshots":[{"screenshot":"dd0ed5af1eb946c34008ec07e9176bd7e33a1778797b99dec63e2bbe778f90cd.png","timeStamp":1721510989689}],"result":"SUCCESS","precondition":false,"level":1,"lineNumber":0,"children":[{"number":6,"description":"Juan clicks on Username field","duration":296,"startTime":"2024-07-20T16:29:49.009020200-05:00[America/Bogota]","screenshots":[{"screenshot":"f52e6411665303a29c483132bdf8ec326778b6333e694c910adf513ef4cebc5e.png","timeStamp":1721510989305}],"result":"SUCCESS","precondition":false,"level":2,"lineNumber":0},{"number":7,"description":"Juan enters \u0027Juan9090\u0027 into Username field","duration":369,"startTime":"2024-07-20T16:29:49.312856900-05:00[America/Bogota]","screenshots":[{"screenshot":"dd0ed5af1eb946c34008ec07e9176bd7e33a1778797b99dec63e2bbe778f90cd.png","timeStamp":1721510989681}],"result":"SUCCESS","precondition":false,"level":2,"lineNumber":0}]}]},{"number":8,"description":"And enter the password \"123\"","duration":396,"startTime":"2024-07-20T16:29:49.697943400-05:00[America/Bogota]","screenshots":[{"screenshot":"c8b04e1eb19e9f4211a231aa50874d1df90738ebc42e9f0211c6fa840accc976.png","timeStamp":1721510990094}],"result":"SUCCESS","precondition":false,"level":0,"lineNumber":0,"children":[{"number":9,"description":"Juan fill password","duration":382,"startTime":"2024-07-20T16:29:49.703945500-05:00[America/Bogota]","screenshots":[{"screenshot":"c8b04e1eb19e9f4211a231aa50874d1df90738ebc42e9f0211c6fa840accc976.png","timeStamp":1721510990086}],"result":"SUCCESS","precondition":false,"level":1,"lineNumber":0,"children":[{"number":10,"description":"Juan enters \u0027123\u0027 into Password field","duration":367,"startTime":"2024-07-20T16:29:49.710947200-05:00[America/Bogota]","screenshots":[{"screenshot":"c8b04e1eb19e9f4211a231aa50874d1df90738ebc42e9f0211c6fa840accc976.png","timeStamp":1721510990078}],"result":"SUCCESS","precondition":false,"level":2,"lineNumber":0}]}]},{"number":11,"description":"And submit the registration form","duration":314,"startTime":"2024-07-20T16:29:50.095028300-05:00[America/Bogota]","screenshots":[{"screenshot":"c28d4cbaf4115fccad780170414ae71bc625e4ede5564c7624fd9576b4848596.png","timeStamp":1721510990409}],"result":"SUCCESS","precondition":false,"level":0,"lineNumber":0,"children":[{"number":12,"description":"Juan submit registration form","duration":300,"startTime":"2024-07-20T16:29:50.100030200-05:00[America/Bogota]","screenshots":[{"screenshot":"c28d4cbaf4115fccad780170414ae71bc625e4ede5564c7624fd9576b4848596.png","timeStamp":1721510990400}],"result":"SUCCESS","precondition":false,"level":1,"lineNumber":0,"children":[{"number":13,"description":"Juan clicks on Submit button","duration":286,"startTime":"2024-07-20T16:29:50.106031800-05:00[America/Bogota]","screenshots":[{"screenshot":"c28d4cbaf4115fccad780170414ae71bc625e4ede5564c7624fd9576b4848596.png","timeStamp":1721510990392}],"result":"SUCCESS","precondition":false,"level":2,"lineNumber":0}]}]},{"number":14,"description":"Then should see a confirmation message \"Sign up successful.\"","duration":696,"startTime":"2024-07-20T16:29:50.410102900-05:00[America/Bogota]","exception":{"errorType":"java.lang.AssertionError","message":"Expected alert message: Sign up successful. but got: This user already exist.","stackTrace":[{"classLoaderName":"app","declaringClass":"co.com.pragma.certification.utest.questions.VerifyAlert","methodName":"performAs","fileName":"VerifyAlert.java","lineNumber":39,"format":1},{"classLoaderName":"app","declaringClass":"co.com.pragma.certification.utest.stepdefinitions.UtestStepDefinitions","methodName":"iShouldSeeAConfirmationMessage","fileName":"UtestStepDefinitions.java","lineNumber":82,"format":1},{"classLoaderName":"app","declaringClass":"cucumber.runner.Runner","methodName":"runPickle","fileName":"Runner.java","lineNumber":80,"format":1}]},"result":"FAILURE","precondition":false,"level":0,"lineNumber":0,"children":[{"number":15,"description":"Juan verify alert","duration":682,"startTime":"2024-07-20T16:29:50.415103300-05:00[America/Bogota]","screenshots":[{"screenshot":"8ed01cc7c85bc19eddcbf4e64b70797b73348bab2268c843d75006c156501d0c.png","htmlSource":"pagesource6796409633550157566.html.txt","timeStamp":1721510991096}],"exception":{"errorType":"java.lang.AssertionError","message":"Expected alert message: Sign up successful. but got: This user already exist.","stackTrace":[{"classLoaderName":"app","declaringClass":"co.com.pragma.certification.utest.questions.VerifyAlert","methodName":"performAs","fileName":"VerifyAlert.java","lineNumber":39,"format":1},{"classLoaderName":"app","declaringClass":"co.com.pragma.certification.utest.stepdefinitions.UtestStepDefinitions","methodName":"iShouldSeeAConfirmationMessage","fileName":"UtestStepDefinitions.java","lineNumber":82,"format":1},{"classLoaderName":"app","declaringClass":"cucumber.runner.Runner","methodName":"runPickle","fileName":"Runner.java","lineNumber":80,"format":1}]},"result":"FAILURE","precondition":false,"level":1,"lineNumber":0}]}],"userStory":{"id":"add-to-cart-functionality","storyName":"Add to cart functionality","path":"src/test/resources/features/utest.feature","narrative":"  As a user\n  I want to be able to add products to the cart\n  So that I can purchase them later","type":"feature"},"featureTag":{"name":"Features/Add to cart functionality","type":"feature","displayName":"Features/Add to cart functionality"},"title":"Create a new user account","backgroundTitle":"","backgroundDescription":"","tags":[{"name":"scenario2","type":"tag","displayName":"scenario2"},{"name":"Add to cart functionality","type":"feature","displayName":"Add to cart functionality"},{"name":"scenarios","type":"tag","displayName":"scenarios"}],"startTime":"2024-07-20T16:29:41.925163500-05:00[America/Bogota]","duration":9189,"testFailureCause":{"errorType":"java.lang.AssertionError","message":"Expected alert message: Sign up successful. but got: This user already exist.","stackTrace":[{"classLoaderName":"app","declaringClass":"co.com.pragma.certification.utest.questions.VerifyAlert","methodName":"performAs","fileName":"VerifyAlert.java","lineNumber":39,"format":1},{"classLoaderName":"app","declaringClass":"co.com.pragma.certification.utest.stepdefinitions.UtestStepDefinitions","methodName":"iShouldSeeAConfirmationMessage","fileName":"UtestStepDefinitions.java","lineNumber":82,"format":1},{"classLoaderName":"app","declaringClass":"cucumber.runner.Runner","methodName":"runPickle","fileName":"Runner.java","lineNumber":80,"format":1}]},"testFailureClassname":"java.lang.AssertionError","testFailureMessage":"Expected alert message: Sign up successful. but got: This user already exist.","testFailureSummary":"FAILURE;java.lang.AssertionError;Expected alert message: Sign up successful. but got: This user already exist.;VerifyAlert.java","projectKey":"","annotatedResult":"FAILURE","sessionId":"289c2e38c60bc6648903b215e20af9a7","driver":"chrome","isManualTestingUpToDate":false,"manual":false,"testSource":"Cucumber","actors":[{"name":"Juan","can":["browse the web"]}],"result":"FAILURE"}